ai_trackdown_pytools/__init__.py
ai_trackdown_pytools/__version__.py
ai_trackdown_pytools/cli.py
ai_trackdown_pytools/exceptions.py
ai_trackdown_pytools/py.typed
ai_trackdown_pytools/version.py
ai_trackdown_pytools/commands/__init__.py
ai_trackdown_pytools/commands/ai.py
ai_trackdown_pytools/commands/bug.py
ai_trackdown_pytools/commands/comment.py
ai_trackdown_pytools/commands/create.py
ai_trackdown_pytools/commands/epic.py
ai_trackdown_pytools/commands/index.py
ai_trackdown_pytools/commands/init.py
ai_trackdown_pytools/commands/issue.py
ai_trackdown_pytools/commands/migrate.py
ai_trackdown_pytools/commands/portfolio.py
ai_trackdown_pytools/commands/pr.py
ai_trackdown_pytools/commands/search.py
ai_trackdown_pytools/commands/status.py
ai_trackdown_pytools/commands/sync.py
ai_trackdown_pytools/commands/task.py
ai_trackdown_pytools/commands/template.py
ai_trackdown_pytools/commands/validate.py
ai_trackdown_pytools/commands/validate_typer.py
ai_trackdown_pytools/core/__init__.py
ai_trackdown_pytools/core/compatibility.py
ai_trackdown_pytools/core/config.py
ai_trackdown_pytools/core/constants.py
ai_trackdown_pytools/core/exceptions.py
ai_trackdown_pytools/core/models.py
ai_trackdown_pytools/core/project.py
ai_trackdown_pytools/core/task.py
ai_trackdown_pytools/core/workflow.py
ai_trackdown_pytools/schemas/bug.json
ai_trackdown_pytools/schemas/epic.json
ai_trackdown_pytools/schemas/issue.json
ai_trackdown_pytools/schemas/pr.json
ai_trackdown_pytools/schemas/project.json
ai_trackdown_pytools/schemas/task.json
ai_trackdown_pytools/templates/bug/default.yaml
ai_trackdown_pytools/templates/epic/default.yaml
ai_trackdown_pytools/templates/issue/default.yaml
ai_trackdown_pytools/templates/pr/default.yaml
ai_trackdown_pytools/templates/project/default.yaml
ai_trackdown_pytools/templates/task/default.yaml
ai_trackdown_pytools/utils/__init__.py
ai_trackdown_pytools/utils/comments.py
ai_trackdown_pytools/utils/console.py
ai_trackdown_pytools/utils/editor.py
ai_trackdown_pytools-1.5.11.dist-info/METADATA
ai_trackdown_pytools-1.5.11.dist-info/WHEEL
ai_trackdown_pytools-1.5.11.dist-info/entry_points.txt
ai_trackdown_pytools-1.5.11.dist-info/licenses/LICENSE
ai_trackdown_pytools-1.5.11.dist-info/RECORD
