Metadata-Version: 2.4
Name: ai-trackdown-pytools
Version: 1.5.11
Summary: Modern Python CLI tools for AI project tracking and task management
Project-URL: Homepage, https://ai-trackdown.com
Project-URL: Documentation, https://ai-trackdown-pytools.readthedocs.io/
Project-URL: Repository, https://github.com/ai-trackdown/ai-trackdown-pytools.git
Project-URL: Bug Tracker, https://github.com/ai-trackdown/ai-trackdown-pytools/issues
Project-URL: Changelog, https://github.com/ai-trackdown/ai-trackdown-pytools/blob/main/CHANGELOG.md
Project-URL: Source Code, https://github.com/ai-trackdown/ai-trackdown-pytools
Project-URL: Discord, https://discord.gg/ai-trackdown
Project-URL: Twitter, https://twitter.com/aitrackdown
Project-URL: Funding, https://github.com/sponsors/ai-trackdown
Author-email: AI Trackdown Team <dev@ai-trackdown.com>
Maintainer-email: AI Trackdown Team <support@ai-trackdown.com>
License: MIT
License-File: LICENSE
Keywords: agile,ai,artificial-intelligence,cli,git,kanban,machine-learning,productivity,project-management,pydantic,rich,scrum,task-management,tasks,terminal,tracking,typer,workflow
Classifier: Development Status :: 5 - Production/Stable
Classifier: Environment :: Console
Classifier: Framework :: Pydantic
Classifier: Framework :: Pydantic :: 2
Classifier: Intended Audience :: Developers
Classifier: Intended Audience :: Information Technology
Classifier: Intended Audience :: Science/Research
Classifier: License :: OSI Approved :: MIT License
Classifier: Natural Language :: English
Classifier: Operating System :: MacOS :: MacOS X
Classifier: Operating System :: Microsoft :: Windows
Classifier: Operating System :: OS Independent
Classifier: Operating System :: POSIX :: Linux
Classifier: Programming Language :: Python :: 3
Classifier: Programming Language :: Python :: 3.8
Classifier: Programming Language :: Python :: 3.9
Classifier: Programming Language :: Python :: 3.10
Classifier: Programming Language :: Python :: 3.11
Classifier: Programming Language :: Python :: 3.12
Classifier: Programming Language :: Python :: Implementation :: CPython
Classifier: Topic :: Office/Business :: Scheduling
Classifier: Topic :: Scientific/Engineering :: Artificial Intelligence
Classifier: Topic :: Software Development
Classifier: Topic :: Software Development :: Bug Tracking
Classifier: Topic :: Software Development :: Documentation
Classifier: Topic :: Software Development :: Version Control
Classifier: Topic :: Software Development :: Version Control :: Git
Classifier: Topic :: Utilities
Classifier: Typing :: Typed
Requires-Python: >=3.8
Requires-Dist: gitpython<4.0.0,>=3.1.40
Requires-Dist: jinja2<4.0.0,>=3.1.0
Requires-Dist: jsonschema<5.0.0,>=4.17.0
Requires-Dist: pathspec<1.0.0,>=0.11.0
Requires-Dist: pydantic<3.0.0,>=2.0.0
Requires-Dist: pyyaml<7.0,>=6.0
Requires-Dist: rich<14.0.0,>=13.0.0
Requires-Dist: toml<1.0.0,>=0.10.2
Requires-Dist: typer<1.0.0,>=0.9.0
Provides-Extra: all
Requires-Dist: aiohttp<4.0.0,>=3.9.0; extra == 'all'
Requires-Dist: gql[aiohttp]<4.0.0,>=3.4.0; extra == 'all'
Requires-Dist: jira<4.0.0,>=3.5.0; extra == 'all'
Provides-Extra: ci
Requires-Dist: coverage[toml]<8.0.0,>=7.0.0; extra == 'ci'
Requires-Dist: psutil<6.0.0,>=5.9.0; extra == 'ci'
Requires-Dist: pytest-cov<5.0.0,>=4.0.0; extra == 'ci'
Requires-Dist: pytest-github-actions-annotate-failures<1.0.0,>=0.2.0; extra == 'ci'
Requires-Dist: pytest-json-report<2.0.0,>=1.5.0; extra == 'ci'
Provides-Extra: dev
Requires-Dist: bandit[toml]<2.0.0,>=1.7.5; extra == 'dev'
Requires-Dist: black<24.0.0,>=23.0.0; extra == 'dev'
Requires-Dist: build<1.0.0,>=0.10.0; extra == 'dev'
Requires-Dist: bump2version<2.0.0,>=1.0.1; extra == 'dev'
Requires-Dist: check-manifest<1.0,>=0.49; extra == 'dev'
Requires-Dist: commitizen<4.0.0,>=3.0.0; extra == 'dev'
Requires-Dist: coverage[toml]<8.0.0,>=7.0.0; extra == 'dev'
Requires-Dist: flake8-bugbear<24.0.0,>=23.0.0; extra == 'dev'
Requires-Dist: flake8-comprehensions<4.0.0,>=3.14.0; extra == 'dev'
Requires-Dist: flake8-docstrings<2.0.0,>=1.7.0; extra == 'dev'
Requires-Dist: flake8-simplify<1.0.0,>=0.20.0; extra == 'dev'
Requires-Dist: flake8<7.0.0,>=6.0.0; extra == 'dev'
Requires-Dist: isort<6.0.0,>=5.12.0; extra == 'dev'
Requires-Dist: line-profiler<5.0.0,>=4.1.0; extra == 'dev'
Requires-Dist: memory-profiler<1.0.0,>=0.61.0; extra == 'dev'
Requires-Dist: mypy<2.0.0,>=1.5.0; extra == 'dev'
Requires-Dist: pip-audit<3.0.0,>=2.6.0; extra == 'dev'
Requires-Dist: pre-commit<4.0.0,>=3.0.0; extra == 'dev'
Requires-Dist: psutil<6.0.0,>=5.9.0; extra == 'dev'
Requires-Dist: pydocstyle<7.0.0,>=6.3.0; extra == 'dev'
Requires-Dist: pytest-asyncio<1.0.0,>=0.21.0; extra == 'dev'
Requires-Dist: pytest-benchmark<5.0.0,>=4.0.0; extra == 'dev'
Requires-Dist: pytest-cov<5.0.0,>=4.0.0; extra == 'dev'
Requires-Dist: pytest-html<4.0.0,>=3.1.0; extra == 'dev'
Requires-Dist: pytest-mock<4.0.0,>=3.10.0; extra == 'dev'
Requires-Dist: pytest-stress<2.0.0,>=1.0.0; extra == 'dev'
Requires-Dist: pytest-timeout<3.0.0,>=2.1.0; extra == 'dev'
Requires-Dist: pytest-xdist<4.0.0,>=3.0.0; extra == 'dev'
Requires-Dist: pytest<8.0.0,>=7.0.0; extra == 'dev'
Requires-Dist: radon<7.0.0,>=6.0.1; extra == 'dev'
Requires-Dist: ruff<1.0.0,>=0.1.0; extra == 'dev'
Requires-Dist: safety<3.0.0,>=2.3.0; extra == 'dev'
Requires-Dist: semgrep<2.0.0,>=1.45.0; extra == 'dev'
Requires-Dist: tox<5.0.0,>=4.0.0; extra == 'dev'
Requires-Dist: twine<5.0.0,>=4.0.0; extra == 'dev'
Requires-Dist: types-pyyaml<7.0.0,>=6.0.0; extra == 'dev'
Requires-Dist: types-requests<3.0.0,>=2.31.0; extra == 'dev'
Requires-Dist: types-toml<1.0.0,>=0.10.0; extra == 'dev'
Requires-Dist: vulture<3.0,>=2.7; extra == 'dev'
Requires-Dist: xenon<1.0.0,>=0.9.0; extra == 'dev'
Provides-Extra: docs
Requires-Dist: myst-parser<3.0.0,>=2.0.0; extra == 'docs'
Requires-Dist: sphinx-rtd-theme<2.0.0,>=1.2.0; extra == 'docs'
Requires-Dist: sphinx<8.0.0,>=6.0.0; extra == 'docs'
Provides-Extra: performance
Requires-Dist: line-profiler<5.0.0,>=4.1.0; extra == 'performance'
Requires-Dist: memory-profiler<1.0.0,>=0.61.0; extra == 'performance'
Requires-Dist: psutil<6.0.0,>=5.9.0; extra == 'performance'
Requires-Dist: py-spy<1.0.0,>=0.3.14; extra == 'performance'
Requires-Dist: pytest-benchmark<5.0.0,>=4.0.0; extra == 'performance'
Requires-Dist: pytest-stress<2.0.0,>=1.0.0; extra == 'performance'
Provides-Extra: security
Requires-Dist: bandit[toml]<2.0.0,>=1.7.5; extra == 'security'
Requires-Dist: cyclonedx-bom<5.0.0,>=4.0.0; extra == 'security'
Requires-Dist: pip-audit<3.0.0,>=2.6.0; extra == 'security'
Requires-Dist: pip-licenses<5.0.0,>=4.3.0; extra == 'security'
Requires-Dist: safety<3.0.0,>=2.3.0; extra == 'security'
Requires-Dist: semgrep<2.0.0,>=1.45.0; extra == 'security'
Provides-Extra: sync
Requires-Dist: aiohttp<4.0.0,>=3.9.0; extra == 'sync'
Requires-Dist: gql[aiohttp]<4.0.0,>=3.4.0; extra == 'sync'
Requires-Dist: jira<4.0.0,>=3.5.0; extra == 'sync'
Provides-Extra: test
Requires-Dist: coverage[toml]<8.0.0,>=7.0.0; extra == 'test'
Requires-Dist: pytest-asyncio<1.0.0,>=0.21.0; extra == 'test'
Requires-Dist: pytest-cov<5.0.0,>=4.0.0; extra == 'test'
Requires-Dist: pytest-mock<4.0.0,>=3.10.0; extra == 'test'
Requires-Dist: pytest-timeout<3.0.0,>=2.1.0; extra == 'test'
Requires-Dist: pytest-xdist<4.0.0,>=3.0.0; extra == 'test'
Requires-Dist: pytest<8.0.0,>=7.0.0; extra == 'test'
